writerblocks/__init__.py
writerblocks/backend.py
writerblocks/cli.py
writerblocks/common.py
writerblocks/gui.py
writerblocks-0.3.dist-info/COPYING
writerblocks-0.3.dist-info/METADATA
writerblocks-0.3.dist-info/WHEEL
writerblocks-0.3.dist-info/entry_points.txt
writerblocks-0.3.dist-info/top_level.txt
writerblocks-0.3.dist-info/RECORD
