Metadata-Version: 2.1
Name: writerblocks
Version: 0.3
Summary: A toolkit for writing stories in a modular way.
Home-page: https://github.com/mimadrone/writerblocks
Author: M. I. Madrone
Author-email: mimadrone@gmx.com
License: GPLv3
Keywords: writing
Platform: UNKNOWN
Classifier: Development Status :: 3 - Alpha
Classifier: Environment :: Console
Classifier: License :: OSI Approved :: GNU General Public License v3 (GPLv3)
Classifier: Topic :: Text Processing
Requires-Python: >=3.5
Requires-Dist: pypandoc
Requires-Dist: PyYAML
Requires-Dist: Kivy
